{
    "LVcustomers":[
        {
            "busId":8,
            "coded_ean":"SOG0020007132",
            "connectionCapacity":5.75,
            "deviceId":0,
            "device_profile_file":"Load profiles POLA/2020/profile_SOG0020007132_2020.csv",
            "exclusiveNight":false,
            "phases":[
                3
            ],
            "yearlyNetConsumption":1716.5372424771263,
            "yearlyNetReactiveConsumption":161.82551331880225
        },
        {
            "busId":11,
            "coded_ean":"ZIV0036291246",
            "connectionCapacity":5.2,
            "deviceId":1,
            "device_profile_file":"Load profiles POLA/2020/profile_ZIV0036291246_2020.csv",
            "exclusiveNight":false,
            "phases":[
                1,
                2,
                3
            ],
            "yearlyNetConsumption":4972.527314445433,
            "yearlyNetReactiveConsumption":646.2218861812325
        },
        {
            "busId":13,
            "coded_ean":"ZIV0034795690",
            "connectionCapacity":3.45,
            "deviceId":2,
            "device_profile_file":"Load profiles POLA/2020/profile_ZIV0034795690_2020.csv",
            "exclusiveNight":false,
            "phases":[
                2
            ],
            "yearlyNetConsumption":1287.9390714870428,
            "yearlyNetReactiveConsumption":147.34398426181403
        },
        {
            "busId":15,
            "coded_ean":"ZIV0034813734",
            "connectionCapacity":3.45,
            "deviceId":3,
            "device_profile_file":"Load profiles POLA/2020/profile_ZIV0034813734_2020.csv",
            "exclusiveNight":false,
            "phases":[
                1
            ],
            "yearlyNetConsumption":1644.9592878503843,
            "yearlyNetReactiveConsumption":143.74947047043267
        },
        {
            "busId":18,
            "coded_ean":"ZIV0034810650",
            "connectionCapacity":4.4,
            "deviceId":4,
            "device_profile_file":"Load profiles POLA/2020/profile_ZIV0034810650_2020.csv",
            "exclusiveNight":false,
            "phases":[
                2
            ],
            "yearlyNetConsumption":1058.3323733632055,
            "yearlyNetReactiveConsumption":150.97491631800227
        },
        {
            "busId":21,
            "coded_ean":"ZIV0034810649",
            "connectionCapacity":3.3,
            "deviceId":5,
            "device_profile_file":"Load profiles POLA/2020/profile_ZIV0034810649_2020.csv",
            "exclusiveNight":false,
            "phases":[
                3
            ],
            "yearlyNetConsumption":1458.2729152199197,
            "yearlyNetReactiveConsumption":159.37281610970564
        },
        {
            "busId":27,
            "coded_ean":"ZIV0049974773",
            "connectionCapacity":20.79,
            "deviceId":6,
            "device_profile_file":"Load profiles POLA/2020/profile_ZIV0049974773_2020.csv",
            "exclusiveNight":false,
            "phases":[
                1,
                2,
                3
            ],
            "yearlyNetConsumption":3095.8018874161544,
            "yearlyNetReactiveConsumption":562.5876535947433
        },
        {
            "busId":32,
            "coded_ean":"ZIV0046994919",
            "connectionCapacity":5.75,
            "deviceId":7,
            "device_profile_file":"Load profiles POLA/2020/profile_ZIV0046994919_2020.csv",
            "exclusiveNight":false,
            "phases":[
                2
            ],
            "yearlyNetConsumption":1495.7842442845329,
            "yearlyNetReactiveConsumption":176.73923341328677
        },
        {
            "busId":34,
            "coded_ean":"ZIV0045777227",
            "connectionCapacity":5.75,
            "deviceId":8,
            "device_profile_file":"Load profiles POLA/2020/profile_ZIV0045777227_2020.csv",
            "exclusiveNight":false,
            "phases":[
                2
            ],
            "yearlyNetConsumption":1710.6420807919512,
            "yearlyNetReactiveConsumption":134.55235049679973
        },
        {
            "busId":36,
            "coded_ean":"ZIV0045777225",
            "connectionCapacity":6.6,
            "deviceId":9,
            "device_profile_file":"Load profiles POLA/2020/profile_ZIV0045777225_2020.csv",
            "exclusiveNight":false,
            "phases":[
                1
            ],
            "yearlyNetConsumption":1597.3946539467536,
            "yearlyNetReactiveConsumption":158.19923059267796
        }
    ],
    "solarGens":[]
}