{
    "LVcustomers":[
        {
            "busId":7,
            "coded_ean":"SAG0145436133",
            "connectionCapacity":3.45,
            "deviceId":0,
            "device_profile_file":"Load profiles POLA/2020/profile_SAG0145436133_2020.csv",
            "exclusiveNight":false,
            "phases":[
                2
            ],
            "yearlyNetConsumption":1631.3399395804568,
            "yearlyNetReactiveConsumption":180.7862729316232
        },
        {
            "busId":7,
            "coded_ean":"ZIV0034862983",
            "connectionCapacity":4.6,
            "deviceId":1,
            "device_profile_file":"Load profiles POLA/2020/profile_ZIV0034862983_2020.csv",
            "exclusiveNight":false,
            "phases":[
                2
            ],
            "yearlyNetConsumption":1611.4537671235062,
            "yearlyNetReactiveConsumption":127.65307478723287
        },
        {
            "busId":7,
            "coded_ean":"ZIV0034919895",
            "connectionCapacity":3.45,
            "deviceId":2,
            "device_profile_file":"Load profiles POLA/2020/profile_ZIV0034919895_2020.csv",
            "exclusiveNight":false,
            "phases":[
                1
            ],
            "yearlyNetConsumption":1326.9734179221193,
            "yearlyNetReactiveConsumption":122.64342180200754
        },
        {
            "busId":7,
            "coded_ean":"ZIV0036292200",
            "connectionCapacity":13.86,
            "deviceId":3,
            "device_profile_file":"Load profiles POLA/2020/profile_ZIV0036292200_2020.csv",
            "exclusiveNight":false,
            "phases":[
                1,
                2,
                3
            ],
            "yearlyNetConsumption":7167.8748869554165,
            "yearlyNetReactiveConsumption":462.35996301223247
        },
        {
            "busId":7,
            "coded_ean":"ZIV0036294363",
            "connectionCapacity":13.86,
            "deviceId":4,
            "device_profile_file":"Load profiles POLA/2020/profile_ZIV0036294363_2020.csv",
            "exclusiveNight":false,
            "phases":[
                1,
                2,
                3
            ],
            "yearlyNetConsumption":5493.596348044034,
            "yearlyNetReactiveConsumption":475.6124020065277
        },
        {
            "busId":7,
            "coded_ean":"ZIV0040327474",
            "connectionCapacity":4.4,
            "deviceId":5,
            "device_profile_file":"Load profiles POLA/2020/profile_ZIV0040327474_2020.csv",
            "exclusiveNight":false,
            "phases":[
                1
            ],
            "yearlyNetConsumption":1486.3077162591624,
            "yearlyNetReactiveConsumption":123.0831957868745
        },
        {
            "busId":7,
            "coded_ean":"ZIV0046917217",
            "connectionCapacity":4.4,
            "deviceId":6,
            "device_profile_file":"Load profiles POLA/2020/profile_ZIV0046917217_2020.csv",
            "exclusiveNight":false,
            "phases":[
                1
            ],
            "yearlyNetConsumption":1503.212433990905,
            "yearlyNetReactiveConsumption":102.8944957033704
        },
        {
            "busId":7,
            "coded_ean":"ZIV0046917221",
            "connectionCapacity":4.6,
            "deviceId":7,
            "device_profile_file":"Load profiles POLA/2020/profile_ZIV0046917221_2020.csv",
            "exclusiveNight":false,
            "phases":[
                2
            ],
            "yearlyNetConsumption":1095.8369614750136,
            "yearlyNetReactiveConsumption":181.04449628815297
        },
        {
            "busId":7,
            "coded_ean":"ZIV0046924363",
            "connectionCapacity":4.6,
            "deviceId":8,
            "device_profile_file":"Load profiles POLA/2020/profile_ZIV0046924363_2020.csv",
            "exclusiveNight":false,
            "phases":[
                1
            ],
            "yearlyNetConsumption":1316.7275393646617,
            "yearlyNetReactiveConsumption":134.28209822557125
        },
        {
            "busId":7,
            "coded_ean":"ZIV0046924364",
            "connectionCapacity":5.75,
            "deviceId":9,
            "device_profile_file":"Load profiles POLA/2020/profile_ZIV0046924364_2020.csv",
            "exclusiveNight":false,
            "phases":[
                3
            ],
            "yearlyNetConsumption":1280.9429246035734,
            "yearlyNetReactiveConsumption":95.46494176371019
        },
        {
            "busId":7,
            "coded_ean":"ZIV0046924365",
            "connectionCapacity":2.3,
            "deviceId":10,
            "device_profile_file":"Load profiles POLA/2020/profile_ZIV0046924365_2020.csv",
            "exclusiveNight":false,
            "phases":[
                3
            ],
            "yearlyNetConsumption":978.8248904508735,
            "yearlyNetReactiveConsumption":171.68646314059984
        },
        {
            "busId":7,
            "coded_ean":"ZIV0046924366",
            "connectionCapacity":3.45,
            "deviceId":11,
            "device_profile_file":"Load profiles POLA/2020/profile_ZIV0046924366_2020.csv",
            "exclusiveNight":false,
            "phases":[
                2
            ],
            "yearlyNetConsumption":1629.9849386555688,
            "yearlyNetReactiveConsumption":128.18665200991373
        },
        {
            "busId":7,
            "coded_ean":"ZIV0046924367",
            "connectionCapacity":4.6,
            "deviceId":12,
            "device_profile_file":"Load profiles POLA/2020/profile_ZIV0046924367_2020.csv",
            "exclusiveNight":false,
            "phases":[
                1
            ],
            "yearlyNetConsumption":1669.4805259320478,
            "yearlyNetReactiveConsumption":147.3737784653342
        },
        {
            "busId":7,
            "coded_ean":"ZIV0046924368",
            "connectionCapacity":4.4,
            "deviceId":13,
            "device_profile_file":"Load profiles POLA/2020/profile_ZIV0046924368_2020.csv",
            "exclusiveNight":false,
            "phases":[
                3
            ],
            "yearlyNetConsumption":1750.5126673485815,
            "yearlyNetReactiveConsumption":96.64774542533516
        },
        {
            "busId":7,
            "coded_ean":"ZIV0046924369",
            "connectionCapacity":4.4,
            "deviceId":14,
            "device_profile_file":"Load profiles POLA/2020/profile_ZIV0046924369_2020.csv",
            "exclusiveNight":false,
            "phases":[
                3
            ],
            "yearlyNetConsumption":1530.6293307607932,
            "yearlyNetReactiveConsumption":148.9483548728897
        },
        {
            "busId":7,
            "coded_ean":"ZIV0046924370",
            "connectionCapacity":5.5,
            "deviceId":15,
            "device_profile_file":"Load profiles POLA/2020/profile_ZIV0046924370_2020.csv",
            "exclusiveNight":false,
            "phases":[
                3
            ],
            "yearlyNetConsumption":1736.117726225845,
            "yearlyNetReactiveConsumption":137.4534641093166
        },
        {
            "busId":7,
            "coded_ean":"ZIV0046924371",
            "connectionCapacity":4.4,
            "deviceId":16,
            "device_profile_file":"Load profiles POLA/2020/profile_ZIV0046924371_2020.csv",
            "exclusiveNight":false,
            "phases":[
                3
            ],
            "yearlyNetConsumption":1739.9782162418255,
            "yearlyNetReactiveConsumption":153.5024309612547
        },
        {
            "busId":7,
            "coded_ean":"ZIV0046924372",
            "connectionCapacity":3.3,
            "deviceId":17,
            "device_profile_file":"Load profiles POLA/2020/profile_ZIV0046924372_2020.csv",
            "exclusiveNight":false,
            "phases":[
                1
            ],
            "yearlyNetConsumption":926.7080937712012,
            "yearlyNetReactiveConsumption":166.52286892498003
        },
        {
            "busId":7,
            "coded_ean":"ZIV0046924593",
            "connectionCapacity":4.6,
            "deviceId":18,
            "device_profile_file":"Load profiles POLA/2020/profile_ZIV0046924593_2020.csv",
            "exclusiveNight":false,
            "phases":[
                2
            ],
            "yearlyNetConsumption":1799.2847167241157,
            "yearlyNetReactiveConsumption":150.63619234140685
        },
        {
            "busId":7,
            "coded_ean":"ZIV0046924594",
            "connectionCapacity":5.5,
            "deviceId":19,
            "device_profile_file":"Load profiles POLA/2020/profile_ZIV0046924594_2020.csv",
            "exclusiveNight":false,
            "phases":[
                2
            ],
            "yearlyNetConsumption":1545.0262262617334,
            "yearlyNetReactiveConsumption":150.5879171444864
        },
        {
            "busId":7,
            "coded_ean":"ZIV0046924595",
            "connectionCapacity":4.6,
            "deviceId":20,
            "device_profile_file":"Load profiles POLA/2020/profile_ZIV0046924595_2020.csv",
            "exclusiveNight":false,
            "phases":[
                2
            ],
            "yearlyNetConsumption":1404.016707717807,
            "yearlyNetReactiveConsumption":96.66037357227849
        },
        {
            "busId":7,
            "coded_ean":"ZIV0046924598",
            "connectionCapacity":4.6,
            "deviceId":21,
            "device_profile_file":"Load profiles POLA/2020/profile_ZIV0046924598_2020.csv",
            "exclusiveNight":false,
            "phases":[
                3
            ],
            "yearlyNetConsumption":1916.401265486953,
            "yearlyNetReactiveConsumption":148.53741441795458
        },
        {
            "busId":7,
            "coded_ean":"ZIV0046924599",
            "connectionCapacity":4.4,
            "deviceId":22,
            "device_profile_file":"Load profiles POLA/2020/profile_ZIV0046924599_2020.csv",
            "exclusiveNight":false,
            "phases":[
                1
            ],
            "yearlyNetConsumption":1453.5913481152734,
            "yearlyNetReactiveConsumption":137.32381291463517
        },
        {
            "busId":7,
            "coded_ean":"ZIV0046924600",
            "connectionCapacity":4.6,
            "deviceId":23,
            "device_profile_file":"Load profiles POLA/2020/profile_ZIV0046924600_2020.csv",
            "exclusiveNight":false,
            "phases":[
                3
            ],
            "yearlyNetConsumption":1127.5954953365685,
            "yearlyNetReactiveConsumption":94.61099532887752
        },
        {
            "busId":7,
            "coded_ean":"ZIV0046924601",
            "connectionCapacity":4.6,
            "deviceId":24,
            "device_profile_file":"Load profiles POLA/2020/profile_ZIV0046924601_2020.csv",
            "exclusiveNight":false,
            "phases":[
                3
            ],
            "yearlyNetConsumption":1582.881922081088,
            "yearlyNetReactiveConsumption":121.07339993927106
        },
        {
            "busId":9,
            "coded_ean":"SAG0125356591",
            "connectionCapacity":4.6,
            "deviceId":25,
            "device_profile_file":"Load profiles POLA/2020/profile_SAG0125356591_2020.csv",
            "exclusiveNight":false,
            "phases":[
                2
            ],
            "yearlyNetConsumption":1270.4711128404874,
            "yearlyNetReactiveConsumption":129.9271873611985
        },
        {
            "busId":9,
            "coded_ean":"SAG0125356593",
            "connectionCapacity":4.6,
            "deviceId":26,
            "device_profile_file":"Load profiles POLA/2020/profile_SAG0125356593_2020.csv",
            "exclusiveNight":false,
            "phases":[
                3
            ],
            "yearlyNetConsumption":1401.0298911138839,
            "yearlyNetReactiveConsumption":111.78579533530814
        },
        {
            "busId":9,
            "coded_ean":"SAG0125356596",
            "connectionCapacity":3.45,
            "deviceId":27,
            "device_profile_file":"Load profiles POLA/2020/profile_SAG0125356596_2020.csv",
            "exclusiveNight":false,
            "phases":[
                3
            ],
            "yearlyNetConsumption":1663.9592869962105,
            "yearlyNetReactiveConsumption":158.0588326139572
        },
        {
            "busId":9,
            "coded_ean":"SOG0020076977",
            "connectionCapacity":4.4,
            "deviceId":28,
            "device_profile_file":"Load profiles POLA/2020/profile_SOG0020076977_2020.csv",
            "exclusiveNight":false,
            "phases":[
                1
            ],
            "yearlyNetConsumption":1453.776864125747,
            "yearlyNetReactiveConsumption":189.1648348342481
        },
        {
            "busId":9,
            "coded_ean":"ZIV0034820218",
            "connectionCapacity":4.4,
            "deviceId":29,
            "device_profile_file":"Load profiles POLA/2020/profile_ZIV0034820218_2020.csv",
            "exclusiveNight":false,
            "phases":[
                2
            ],
            "yearlyNetConsumption":1548.6633415002052,
            "yearlyNetReactiveConsumption":127.806130166952
        },
        {
            "busId":9,
            "coded_ean":"ZIV0034820223",
            "connectionCapacity":3.45,
            "deviceId":30,
            "device_profile_file":"Load profiles POLA/2020/profile_ZIV0034820223_2020.csv",
            "exclusiveNight":false,
            "phases":[
                3
            ],
            "yearlyNetConsumption":1709.522436544415,
            "yearlyNetReactiveConsumption":130.11144302328782
        },
        {
            "busId":9,
            "coded_ean":"ZIV0034820224",
            "connectionCapacity":3.45,
            "deviceId":31,
            "device_profile_file":"Load profiles POLA/2020/profile_ZIV0034820224_2020.csv",
            "exclusiveNight":false,
            "phases":[
                2
            ],
            "yearlyNetConsumption":1363.1762375433723,
            "yearlyNetReactiveConsumption":118.85150054702038
        },
        {
            "busId":9,
            "coded_ean":"ZIV0034820226",
            "connectionCapacity":4.6,
            "deviceId":32,
            "device_profile_file":"Load profiles POLA/2020/profile_ZIV0034820226_2020.csv",
            "exclusiveNight":false,
            "phases":[
                2
            ],
            "yearlyNetConsumption":1203.114535358495,
            "yearlyNetReactiveConsumption":171.55045188814066
        },
        {
            "busId":9,
            "coded_ean":"ZIV0034820468",
            "connectionCapacity":4.6,
            "deviceId":33,
            "device_profile_file":"Load profiles POLA/2020/profile_ZIV0034820468_2020.csv",
            "exclusiveNight":false,
            "phases":[
                2
            ],
            "yearlyNetConsumption":1749.9224700826435,
            "yearlyNetReactiveConsumption":127.7725239474058
        },
        {
            "busId":9,
            "coded_ean":"ZIV0034820469",
            "connectionCapacity":4.4,
            "deviceId":34,
            "device_profile_file":"Load profiles POLA/2020/profile_ZIV0034820469_2020.csv",
            "exclusiveNight":false,
            "phases":[
                1
            ],
            "yearlyNetConsumption":1348.004775345144,
            "yearlyNetReactiveConsumption":131.36571758948293
        },
        {
            "busId":9,
            "coded_ean":"ZIV0034820471",
            "connectionCapacity":3.45,
            "deviceId":35,
            "device_profile_file":"Load profiles POLA/2020/profile_ZIV0034820471_2020.csv",
            "exclusiveNight":false,
            "phases":[
                3
            ],
            "yearlyNetConsumption":1503.9080664251978,
            "yearlyNetReactiveConsumption":170.60602947464287
        },
        {
            "busId":9,
            "coded_ean":"ZIV0034820474",
            "connectionCapacity":4.4,
            "deviceId":36,
            "device_profile_file":"Load profiles POLA/2020/profile_ZIV0034820474_2020.csv",
            "exclusiveNight":false,
            "phases":[
                2
            ],
            "yearlyNetConsumption":1595.0101800922519,
            "yearlyNetReactiveConsumption":173.51841005095787
        },
        {
            "busId":9,
            "coded_ean":"ZIV0034820475",
            "connectionCapacity":4.4,
            "deviceId":37,
            "device_profile_file":"Load profiles POLA/2020/profile_ZIV0034820475_2020.csv",
            "exclusiveNight":false,
            "phases":[
                3
            ],
            "yearlyNetConsumption":1493.7758648326496,
            "yearlyNetReactiveConsumption":137.68918445774315
        },
        {
            "busId":9,
            "coded_ean":"ZIV0034820477",
            "connectionCapacity":4.6,
            "deviceId":38,
            "device_profile_file":"Load profiles POLA/2020/profile_ZIV0034820477_2020.csv",
            "exclusiveNight":false,
            "phases":[
                1
            ],
            "yearlyNetConsumption":1545.5548904096884,
            "yearlyNetReactiveConsumption":135.8087604673783
        },
        {
            "busId":9,
            "coded_ean":"ZIV0034820879",
            "connectionCapacity":4.6,
            "deviceId":39,
            "device_profile_file":"Load profiles POLA/2020/profile_ZIV0034820879_2020.csv",
            "exclusiveNight":false,
            "phases":[
                3
            ],
            "yearlyNetConsumption":1786.1476480092479,
            "yearlyNetReactiveConsumption":131.6557946827714
        },
        {
            "busId":9,
            "coded_ean":"ZIV0034820881",
            "connectionCapacity":4.6,
            "deviceId":40,
            "device_profile_file":"Load profiles POLA/2020/profile_ZIV0034820881_2020.csv",
            "exclusiveNight":false,
            "phases":[
                2
            ],
            "yearlyNetConsumption":1023.3694988390023,
            "yearlyNetReactiveConsumption":162.18255112931053
        },
        {
            "busId":9,
            "coded_ean":"ZIV0034820883",
            "connectionCapacity":4.6,
            "deviceId":41,
            "device_profile_file":"Load profiles POLA/2020/profile_ZIV0034820883_2020.csv",
            "exclusiveNight":false,
            "phases":[
                2
            ],
            "yearlyNetConsumption":1413.1280170528553,
            "yearlyNetReactiveConsumption":103.43173413217578
        },
        {
            "busId":9,
            "coded_ean":"ZIV0034820885",
            "connectionCapacity":4.6,
            "deviceId":42,
            "device_profile_file":"Load profiles POLA/2020/profile_ZIV0034820885_2020.csv",
            "exclusiveNight":false,
            "phases":[
                1
            ],
            "yearlyNetConsumption":1429.9660126947172,
            "yearlyNetReactiveConsumption":163.10828577873946
        },
        {
            "busId":9,
            "coded_ean":"ZIV0034820886",
            "connectionCapacity":4.6,
            "deviceId":43,
            "device_profile_file":"Load profiles POLA/2020/profile_ZIV0034820886_2020.csv",
            "exclusiveNight":false,
            "phases":[
                1
            ],
            "yearlyNetConsumption":1324.7030754538432,
            "yearlyNetReactiveConsumption":117.49724739683762
        },
        {
            "busId":9,
            "coded_ean":"ZIV0034820887",
            "connectionCapacity":4.6,
            "deviceId":44,
            "device_profile_file":"Load profiles POLA/2020/profile_ZIV0034820887_2020.csv",
            "exclusiveNight":false,
            "phases":[
                2
            ],
            "yearlyNetConsumption":1431.7084619498746,
            "yearlyNetReactiveConsumption":151.44876936460048
        },
        {
            "busId":9,
            "coded_ean":"ZIV0034821102",
            "connectionCapacity":4.6,
            "deviceId":45,
            "device_profile_file":"Load profiles POLA/2020/profile_ZIV0034821102_2020.csv",
            "exclusiveNight":false,
            "phases":[
                1
            ],
            "yearlyNetConsumption":1381.2669360095656,
            "yearlyNetReactiveConsumption":173.27410847436602
        },
        {
            "busId":9,
            "coded_ean":"ZIV0034821107",
            "connectionCapacity":4.6,
            "deviceId":46,
            "device_profile_file":"Load profiles POLA/2020/profile_ZIV0034821107_2020.csv",
            "exclusiveNight":false,
            "phases":[
                2
            ],
            "yearlyNetConsumption":1303.6691669306165,
            "yearlyNetReactiveConsumption":180.09063291014274
        },
        {
            "busId":9,
            "coded_ean":"ZIV0034859379",
            "connectionCapacity":4.6,
            "deviceId":47,
            "device_profile_file":"Load profiles POLA/2020/profile_ZIV0034859379_2020.csv",
            "exclusiveNight":false,
            "phases":[
                1
            ],
            "yearlyNetConsumption":1169.0676897412263,
            "yearlyNetReactiveConsumption":170.85943158469559
        },
        {
            "busId":9,
            "coded_ean":"ZIV0034859380",
            "connectionCapacity":3.45,
            "deviceId":48,
            "device_profile_file":"Load profiles POLA/2020/profile_ZIV0034859380_2020.csv",
            "exclusiveNight":false,
            "phases":[
                1
            ],
            "yearlyNetConsumption":1117.0164983746579,
            "yearlyNetReactiveConsumption":161.9382617698197
        },
        {
            "busId":9,
            "coded_ean":"ZIV0034859381",
            "connectionCapacity":4.4,
            "deviceId":49,
            "device_profile_file":"Load profiles POLA/2020/profile_ZIV0034859381_2020.csv",
            "exclusiveNight":false,
            "phases":[
                3
            ],
            "yearlyNetConsumption":1744.707146250256,
            "yearlyNetReactiveConsumption":146.95378913592432
        },
        {
            "busId":9,
            "coded_ean":"ZIV0034859382",
            "connectionCapacity":4.6,
            "deviceId":50,
            "device_profile_file":"Load profiles POLA/2020/profile_ZIV0034859382_2020.csv",
            "exclusiveNight":false,
            "phases":[
                1
            ],
            "yearlyNetConsumption":1599.089870194417,
            "yearlyNetReactiveConsumption":166.5388426898526
        },
        {
            "busId":9,
            "coded_ean":"ZIV0034859383",
            "connectionCapacity":4.4,
            "deviceId":51,
            "device_profile_file":"Load profiles POLA/2020/profile_ZIV0034859383_2020.csv",
            "exclusiveNight":false,
            "phases":[
                2
            ],
            "yearlyNetConsumption":1721.796489019909,
            "yearlyNetReactiveConsumption":135.2608317367844
        },
        {
            "busId":9,
            "coded_ean":"ZIV0034859384",
            "connectionCapacity":4.6,
            "deviceId":52,
            "device_profile_file":"Load profiles POLA/2020/profile_ZIV0034859384_2020.csv",
            "exclusiveNight":false,
            "phases":[
                3
            ],
            "yearlyNetConsumption":1456.1058022801005,
            "yearlyNetReactiveConsumption":158.59372488226407
        },
        {
            "busId":9,
            "coded_ean":"ZIV0034859385",
            "connectionCapacity":4.4,
            "deviceId":53,
            "device_profile_file":"Load profiles POLA/2020/profile_ZIV0034859385_2020.csv",
            "exclusiveNight":false,
            "phases":[
                1
            ],
            "yearlyNetConsumption":1233.5714057035443,
            "yearlyNetReactiveConsumption":165.4128346489482
        },
        {
            "busId":9,
            "coded_ean":"ZIV0034859387",
            "connectionCapacity":4.6,
            "deviceId":54,
            "device_profile_file":"Load profiles POLA/2020/profile_ZIV0034859387_2020.csv",
            "exclusiveNight":false,
            "phases":[
                1
            ],
            "yearlyNetConsumption":1361.6669848204772,
            "yearlyNetReactiveConsumption":192.9496977186453
        },
        {
            "busId":9,
            "coded_ean":"ZIV0034859388",
            "connectionCapacity":4.6,
            "deviceId":55,
            "device_profile_file":"Load profiles POLA/2020/profile_ZIV0034859388_2020.csv",
            "exclusiveNight":false,
            "phases":[
                1
            ],
            "yearlyNetConsumption":2002.3066995731165,
            "yearlyNetReactiveConsumption":213.64387578765565
        },
        {
            "busId":9,
            "coded_ean":"ZIV0034859469",
            "connectionCapacity":5.5,
            "deviceId":56,
            "device_profile_file":"Load profiles POLA/2020/profile_ZIV0034859469_2020.csv",
            "exclusiveNight":false,
            "phases":[
                2
            ],
            "yearlyNetConsumption":1742.6700292990593,
            "yearlyNetReactiveConsumption":151.51115882720205
        },
        {
            "busId":9,
            "coded_ean":"ZIV0034917073",
            "connectionCapacity":4.6,
            "deviceId":57,
            "device_profile_file":"Load profiles POLA/2020/profile_ZIV0034917073_2020.csv",
            "exclusiveNight":false,
            "phases":[
                3
            ],
            "yearlyNetConsumption":1159.6113831542152,
            "yearlyNetReactiveConsumption":129.96021776045353
        },
        {
            "busId":9,
            "coded_ean":"ZIV0036292201",
            "connectionCapacity":13.86,
            "deviceId":58,
            "device_profile_file":"Load profiles POLA/2020/profile_ZIV0036292201_2020.csv",
            "exclusiveNight":false,
            "phases":[
                1,
                2,
                3
            ],
            "yearlyNetConsumption":6141.711239219351,
            "yearlyNetReactiveConsumption":481.4288797915166
        },
        {
            "busId":9,
            "coded_ean":"ZIV0046924596",
            "connectionCapacity":4.6,
            "deviceId":59,
            "device_profile_file":"Load profiles POLA/2020/profile_ZIV0046924596_2020.csv",
            "exclusiveNight":false,
            "phases":[
                3
            ],
            "yearlyNetConsumption":1703.6396145100387,
            "yearlyNetReactiveConsumption":166.956435697339
        },
        {
            "busId":9,
            "coded_ean":"ZIV0046924597",
            "connectionCapacity":4.4,
            "deviceId":60,
            "device_profile_file":"Load profiles POLA/2020/profile_ZIV0046924597_2020.csv",
            "exclusiveNight":false,
            "phases":[
                3
            ],
            "yearlyNetConsumption":1878.3492195340075,
            "yearlyNetReactiveConsumption":153.01595354127662
        },
        {
            "busId":9,
            "coded_ean":"ZIV0046975969",
            "connectionCapacity":3.45,
            "deviceId":61,
            "device_profile_file":"Load profiles POLA/2020/profile_ZIV0046975969_2020.csv",
            "exclusiveNight":false,
            "phases":[
                3
            ],
            "yearlyNetConsumption":1158.1677938344346,
            "yearlyNetReactiveConsumption":139.71491204563557
        }
    ],
    "solarGens":[]
}