{
    "LVcustomers":[
        {
            "busId":2,
            "coded_ean":"SAG0125358111",
            "connectionCapacity":3.3,
            "deviceId":0,
            "device_profile_file":"Load profiles POLA/2020/profile_SAG0125358111_2020.csv",
            "exclusiveNight":false,
            "phases":[
                1
            ],
            "yearlyNetConsumption":1535.765131167063,
            "yearlyNetReactiveConsumption":107.57745194756109
        },
        {
            "busId":2,
            "coded_ean":"SAG0125358112",
            "connectionCapacity":5.5,
            "deviceId":1,
            "device_profile_file":"Load profiles POLA/2020/profile_SAG0125358112_2020.csv",
            "exclusiveNight":false,
            "phases":[
                1
            ],
            "yearlyNetConsumption":1612.1908257917758,
            "yearlyNetReactiveConsumption":145.224461536781
        },
        {
            "busId":2,
            "coded_ean":"SAG0125358113",
            "connectionCapacity":3.3,
            "deviceId":2,
            "device_profile_file":"Load profiles POLA/2020/profile_SAG0125358113_2020.csv",
            "exclusiveNight":false,
            "phases":[
                2
            ],
            "yearlyNetConsumption":1650.1536472318328,
            "yearlyNetReactiveConsumption":140.78073593760647
        },
        {
            "busId":2,
            "coded_ean":"SAG0125358114",
            "connectionCapacity":3.3,
            "deviceId":3,
            "device_profile_file":"Load profiles POLA/2020/profile_SAG0125358114_2020.csv",
            "exclusiveNight":false,
            "phases":[
                2
            ],
            "yearlyNetConsumption":1759.1739447393431,
            "yearlyNetReactiveConsumption":162.2371325825315
        },
        {
            "busId":2,
            "coded_ean":"SAG0125358116",
            "connectionCapacity":2.3,
            "deviceId":4,
            "device_profile_file":"Load profiles POLA/2020/profile_SAG0125358116_2020.csv",
            "exclusiveNight":false,
            "phases":[
                2
            ],
            "yearlyNetConsumption":1369.803156535176,
            "yearlyNetReactiveConsumption":135.53058512197555
        },
        {
            "busId":2,
            "coded_ean":"SAG0125358117",
            "connectionCapacity":4.6,
            "deviceId":5,
            "device_profile_file":"Load profiles POLA/2020/profile_SAG0125358117_2020.csv",
            "exclusiveNight":false,
            "phases":[
                3
            ],
            "yearlyNetConsumption":1635.206240137864,
            "yearlyNetReactiveConsumption":109.20377517964882
        },
        {
            "busId":2,
            "coded_ean":"SAG0125358119",
            "connectionCapacity":3.45,
            "deviceId":6,
            "device_profile_file":"Load profiles POLA/2020/profile_SAG0125358119_2020.csv",
            "exclusiveNight":false,
            "phases":[
                1
            ],
            "yearlyNetConsumption":1719.5221896621088,
            "yearlyNetReactiveConsumption":161.47185195504295
        },
        {
            "busId":2,
            "coded_ean":"SAG0125358120",
            "connectionCapacity":3.3,
            "deviceId":7,
            "device_profile_file":"Load profiles POLA/2020/profile_SAG0125358120_2020.csv",
            "exclusiveNight":false,
            "phases":[
                2
            ],
            "yearlyNetConsumption":1268.833756658671,
            "yearlyNetReactiveConsumption":139.16951825333413
        },
        {
            "busId":2,
            "coded_ean":"SAG0125358441",
            "connectionCapacity":4.6,
            "deviceId":8,
            "device_profile_file":"Load profiles POLA/2020/profile_SAG0125358441_2020.csv",
            "exclusiveNight":false,
            "phases":[
                3
            ],
            "yearlyNetConsumption":1373.3421771379708,
            "yearlyNetReactiveConsumption":189.94837219141726
        },
        {
            "busId":2,
            "coded_ean":"SAG0125358442",
            "connectionCapacity":3.45,
            "deviceId":9,
            "device_profile_file":"Load profiles POLA/2020/profile_SAG0125358442_2020.csv",
            "exclusiveNight":false,
            "phases":[
                2
            ],
            "yearlyNetConsumption":1492.003408496383,
            "yearlyNetReactiveConsumption":170.51320811128704
        },
        {
            "busId":2,
            "coded_ean":"SAG0125358444",
            "connectionCapacity":3.3,
            "deviceId":10,
            "device_profile_file":"Load profiles POLA/2020/profile_SAG0125358444_2020.csv",
            "exclusiveNight":false,
            "phases":[
                3
            ],
            "yearlyNetConsumption":1739.2504795918805,
            "yearlyNetReactiveConsumption":94.06605771138794
        },
        {
            "busId":2,
            "coded_ean":"SAG0125358445",
            "connectionCapacity":3.3,
            "deviceId":11,
            "device_profile_file":"Load profiles POLA/2020/profile_SAG0125358445_2020.csv",
            "exclusiveNight":false,
            "phases":[
                2
            ],
            "yearlyNetConsumption":2140.5701538621624,
            "yearlyNetReactiveConsumption":110.93588199459876
        },
        {
            "busId":2,
            "coded_ean":"SAG0125358447",
            "connectionCapacity":3.45,
            "deviceId":12,
            "device_profile_file":"Load profiles POLA/2020/profile_SAG0125358447_2020.csv",
            "exclusiveNight":false,
            "phases":[
                1
            ],
            "yearlyNetConsumption":1603.5632817949574,
            "yearlyNetReactiveConsumption":103.54918913232146
        },
        {
            "busId":2,
            "coded_ean":"SAG0125358449",
            "connectionCapacity":2.3,
            "deviceId":13,
            "device_profile_file":"Load profiles POLA/2020/profile_SAG0125358449_2020.csv",
            "exclusiveNight":false,
            "phases":[
                2
            ],
            "yearlyNetConsumption":1894.2405680225324,
            "yearlyNetReactiveConsumption":87.6130835460266
        },
        {
            "busId":2,
            "coded_ean":"SAG0125358546",
            "connectionCapacity":4.4,
            "deviceId":14,
            "device_profile_file":"Load profiles POLA/2020/profile_SAG0125358546_2020.csv",
            "exclusiveNight":false,
            "phases":[
                2
            ],
            "yearlyNetConsumption":1491.4387144153054,
            "yearlyNetReactiveConsumption":190.43840248606836
        },
        {
            "busId":2,
            "coded_ean":"SAG0125358549",
            "connectionCapacity":3.3,
            "deviceId":15,
            "device_profile_file":"Load profiles POLA/2020/profile_SAG0125358549_2020.csv",
            "exclusiveNight":false,
            "phases":[
                1
            ],
            "yearlyNetConsumption":2012.2375699831482,
            "yearlyNetReactiveConsumption":142.13558121648612
        },
        {
            "busId":2,
            "coded_ean":"SAG0125358574",
            "connectionCapacity":3.3,
            "deviceId":16,
            "device_profile_file":"Load profiles POLA/2020/profile_SAG0125358574_2020.csv",
            "exclusiveNight":false,
            "phases":[
                3
            ],
            "yearlyNetConsumption":996.8689918937043,
            "yearlyNetReactiveConsumption":138.75960446554237
        },
        {
            "busId":2,
            "coded_ean":"SAG0125358580",
            "connectionCapacity":3.3,
            "deviceId":17,
            "device_profile_file":"Load profiles POLA/2020/profile_SAG0125358580_2020.csv",
            "exclusiveNight":false,
            "phases":[
                1
            ],
            "yearlyNetConsumption":1465.2385998826408,
            "yearlyNetReactiveConsumption":142.98563358981244
        },
        {
            "busId":2,
            "coded_ean":"SAG0145421357",
            "connectionCapacity":3.45,
            "deviceId":18,
            "device_profile_file":"Load profiles POLA/2020/profile_SAG0145421357_2020.csv",
            "exclusiveNight":false,
            "phases":[
                3
            ],
            "yearlyNetConsumption":1731.0890422711395,
            "yearlyNetReactiveConsumption":149.34886167261743
        },
        {
            "busId":2,
            "coded_ean":"SAG0145426388",
            "connectionCapacity":2.3,
            "deviceId":19,
            "device_profile_file":"Load profiles POLA/2020/profile_SAG0145426388_2020.csv",
            "exclusiveNight":false,
            "phases":[
                2
            ],
            "yearlyNetConsumption":1357.0794827423376,
            "yearlyNetReactiveConsumption":209.26828600576346
        },
        {
            "busId":2,
            "coded_ean":"ZIV0036295923",
            "connectionCapacity":13.2,
            "deviceId":20,
            "device_profile_file":"Load profiles POLA/2020/profile_ZIV0036295923_2020.csv",
            "exclusiveNight":false,
            "phases":[
                1,
                2,
                3
            ],
            "yearlyNetConsumption":6381.027192539595,
            "yearlyNetReactiveConsumption":290.68699896895646
        },
        {
            "busId":2,
            "coded_ean":"ZIV0045436508",
            "connectionCapacity":6.6,
            "deviceId":21,
            "device_profile_file":"Load profiles POLA/2020/profile_ZIV0045436508_2020.csv",
            "exclusiveNight":false,
            "phases":[
                1,
                2,
                3
            ],
            "yearlyNetConsumption":4992.670612778628,
            "yearlyNetReactiveConsumption":455.81004485671076
        },
        {
            "busId":2,
            "coded_ean":"ZIV0046921905",
            "connectionCapacity":3.45,
            "deviceId":22,
            "device_profile_file":"Load profiles POLA/2020/profile_ZIV0046921905_2020.csv",
            "exclusiveNight":false,
            "phases":[
                2
            ],
            "yearlyNetConsumption":1832.68313050064,
            "yearlyNetReactiveConsumption":180.38331777099907
        },
        {
            "busId":2,
            "coded_ean":"ZIV0046921906",
            "connectionCapacity":3.3,
            "deviceId":23,
            "device_profile_file":"Load profiles POLA/2020/profile_ZIV0046921906_2020.csv",
            "exclusiveNight":false,
            "phases":[
                2
            ],
            "yearlyNetConsumption":1472.737840011317,
            "yearlyNetReactiveConsumption":170.79694303657914
        },
        {
            "busId":2,
            "coded_ean":"ZIV0046921907",
            "connectionCapacity":3.3,
            "deviceId":24,
            "device_profile_file":"Load profiles POLA/2020/profile_ZIV0046921907_2020.csv",
            "exclusiveNight":false,
            "phases":[
                2
            ],
            "yearlyNetConsumption":1563.0303287873337,
            "yearlyNetReactiveConsumption":120.88065742158733
        },
        {
            "busId":2,
            "coded_ean":"ZIV0046921909",
            "connectionCapacity":3.3,
            "deviceId":25,
            "device_profile_file":"Load profiles POLA/2020/profile_ZIV0046921909_2020.csv",
            "exclusiveNight":false,
            "phases":[
                3
            ],
            "yearlyNetConsumption":1159.7353469765026,
            "yearlyNetReactiveConsumption":176.5550006240212
        },
        {
            "busId":2,
            "coded_ean":"ZIV0046921910",
            "connectionCapacity":2.3,
            "deviceId":26,
            "device_profile_file":"Load profiles POLA/2020/profile_ZIV0046921910_2020.csv",
            "exclusiveNight":false,
            "phases":[
                2
            ],
            "yearlyNetConsumption":2005.9544090077165,
            "yearlyNetReactiveConsumption":157.1986700782082
        },
        {
            "busId":2,
            "coded_ean":"ZIV0046921911",
            "connectionCapacity":4.6,
            "deviceId":27,
            "device_profile_file":"Load profiles POLA/2020/profile_ZIV0046921911_2020.csv",
            "exclusiveNight":false,
            "phases":[
                3
            ],
            "yearlyNetConsumption":1816.841791703026,
            "yearlyNetReactiveConsumption":153.14726836886564
        },
        {
            "busId":2,
            "coded_ean":"ZIV0046921912",
            "connectionCapacity":4.4,
            "deviceId":28,
            "device_profile_file":"Load profiles POLA/2020/profile_ZIV0046921912_2020.csv",
            "exclusiveNight":false,
            "phases":[
                3
            ],
            "yearlyNetConsumption":1620.507018857028,
            "yearlyNetReactiveConsumption":166.41333520608265
        },
        {
            "busId":4,
            "coded_ean":"SAG0125358267",
            "connectionCapacity":4.6,
            "deviceId":29,
            "device_profile_file":"Load profiles POLA/2020/profile_SAG0125358267_2020.csv",
            "exclusiveNight":false,
            "phases":[
                3
            ],
            "yearlyNetConsumption":1649.297442824416,
            "yearlyNetReactiveConsumption":145.35493394480045
        },
        {
            "busId":4,
            "coded_ean":"SAG0125358270",
            "connectionCapacity":3.3,
            "deviceId":30,
            "device_profile_file":"Load profiles POLA/2020/profile_SAG0125358270_2020.csv",
            "exclusiveNight":false,
            "phases":[
                2
            ],
            "yearlyNetConsumption":1141.716936848608,
            "yearlyNetReactiveConsumption":130.13396821696548
        },
        {
            "busId":4,
            "coded_ean":"SAG0125358451",
            "connectionCapacity":3.45,
            "deviceId":31,
            "device_profile_file":"Load profiles POLA/2020/profile_SAG0125358451_2020.csv",
            "exclusiveNight":false,
            "phases":[
                3
            ],
            "yearlyNetConsumption":1289.900097190663,
            "yearlyNetReactiveConsumption":135.50371164023184
        },
        {
            "busId":4,
            "coded_ean":"SAG0125358452",
            "connectionCapacity":3.3,
            "deviceId":32,
            "device_profile_file":"Load profiles POLA/2020/profile_SAG0125358452_2020.csv",
            "exclusiveNight":false,
            "phases":[
                1
            ],
            "yearlyNetConsumption":1264.3719243619034,
            "yearlyNetReactiveConsumption":122.63671544465072
        },
        {
            "busId":4,
            "coded_ean":"SAG0125358454",
            "connectionCapacity":4.4,
            "deviceId":33,
            "device_profile_file":"Load profiles POLA/2020/profile_SAG0125358454_2020.csv",
            "exclusiveNight":false,
            "phases":[
                2
            ],
            "yearlyNetConsumption":1038.2398723213369,
            "yearlyNetReactiveConsumption":178.42984293465057
        },
        {
            "busId":4,
            "coded_ean":"SAG0125358455",
            "connectionCapacity":4.4,
            "deviceId":34,
            "device_profile_file":"Load profiles POLA/2020/profile_SAG0125358455_2020.csv",
            "exclusiveNight":false,
            "phases":[
                1
            ],
            "yearlyNetConsumption":1350.9250326316426,
            "yearlyNetReactiveConsumption":173.7206142833514
        },
        {
            "busId":4,
            "coded_ean":"SAG0125358456",
            "connectionCapacity":3.3,
            "deviceId":35,
            "device_profile_file":"Load profiles POLA/2020/profile_SAG0125358456_2020.csv",
            "exclusiveNight":false,
            "phases":[
                1
            ],
            "yearlyNetConsumption":1607.2011824335807,
            "yearlyNetReactiveConsumption":141.79476156780103
        },
        {
            "busId":4,
            "coded_ean":"SAG0125358459",
            "connectionCapacity":3.45,
            "deviceId":36,
            "device_profile_file":"Load profiles POLA/2020/profile_SAG0125358459_2020.csv",
            "exclusiveNight":false,
            "phases":[
                1
            ],
            "yearlyNetConsumption":1332.7649976428797,
            "yearlyNetReactiveConsumption":104.0818043830549
        },
        {
            "busId":4,
            "coded_ean":"ZIV0036295930",
            "connectionCapacity":6.6,
            "deviceId":37,
            "device_profile_file":"Load profiles POLA/2020/profile_ZIV0036295930_2020.csv",
            "exclusiveNight":false,
            "phases":[
                1,
                2,
                3
            ],
            "yearlyNetConsumption":5983.072695767791,
            "yearlyNetReactiveConsumption":470.0400269203975
        },
        {
            "busId":4,
            "coded_ean":"ZIV0046918714",
            "connectionCapacity":3.3,
            "deviceId":38,
            "device_profile_file":"Load profiles POLA/2020/profile_ZIV0046918714_2020.csv",
            "exclusiveNight":false,
            "phases":[
                2
            ],
            "yearlyNetConsumption":1327.329577304299,
            "yearlyNetReactiveConsumption":148.47165800636404
        },
        {
            "busId":4,
            "coded_ean":"ZIV0046918718",
            "connectionCapacity":3.3,
            "deviceId":39,
            "device_profile_file":"Load profiles POLA/2020/profile_ZIV0046918718_2020.csv",
            "exclusiveNight":false,
            "phases":[
                3
            ],
            "yearlyNetConsumption":2014.9234579193571,
            "yearlyNetReactiveConsumption":133.10917866944257
        },
        {
            "busId":4,
            "coded_ean":"ZIV0046918719",
            "connectionCapacity":3.45,
            "deviceId":40,
            "device_profile_file":"Load profiles POLA/2020/profile_ZIV0046918719_2020.csv",
            "exclusiveNight":false,
            "phases":[
                1
            ],
            "yearlyNetConsumption":1514.0223323552796,
            "yearlyNetReactiveConsumption":133.18546098518016
        },
        {
            "busId":4,
            "coded_ean":"ZIV0046918720",
            "connectionCapacity":3.3,
            "deviceId":41,
            "device_profile_file":"Load profiles POLA/2020/profile_ZIV0046918720_2020.csv",
            "exclusiveNight":false,
            "phases":[
                1
            ],
            "yearlyNetConsumption":1468.3006354876618,
            "yearlyNetReactiveConsumption":147.76905887497298
        },
        {
            "busId":4,
            "coded_ean":"ZIV0046918721",
            "connectionCapacity":3.3,
            "deviceId":42,
            "device_profile_file":"Load profiles POLA/2020/profile_ZIV0046918721_2020.csv",
            "exclusiveNight":false,
            "phases":[
                2
            ],
            "yearlyNetConsumption":1379.8826699399015,
            "yearlyNetReactiveConsumption":96.13963046811145
        },
        {
            "busId":4,
            "coded_ean":"ZIV0046918722",
            "connectionCapacity":3.45,
            "deviceId":43,
            "device_profile_file":"Load profiles POLA/2020/profile_ZIV0046918722_2020.csv",
            "exclusiveNight":false,
            "phases":[
                1
            ],
            "yearlyNetConsumption":1787.565391937721,
            "yearlyNetReactiveConsumption":171.84045674891854
        }
    ],
    "solarGens":[]
}